django_generate_secret_key/__init__.py
django_generate_secret_key/tests.py
django_generate_secret_key/management/__init__.py
django_generate_secret_key/management/commands/__init__.py
django_generate_secret_key/management/commands/_private.py
django_generate_secret_key/management/commands/generate_secret_key.py
django_generate_secret_key-1.0.1.dist-info/DESCRIPTION.rst
django_generate_secret_key-1.0.1.dist-info/METADATA
django_generate_secret_key-1.0.1.dist-info/RECORD
django_generate_secret_key-1.0.1.dist-info/WHEEL
django_generate_secret_key-1.0.1.dist-info/metadata.json
django_generate_secret_key-1.0.1.dist-info/top_level.txt
sample/__init__.py
