Metadata-Version: 2.0
Name: django-generate-secret-key
Version: 1.0.1
Summary: A Django application with a command to generate a Django secret key
Home-page: https://github.com/MickaelBergem/django-generate-secret-key
Author: Mickaël Bergem
Author-email: suixo@securem.eu
License: MIT
Keywords: django deployment secret key generation
Platform: UNKNOWN
Classifier: Development Status :: 5 - Production/Stable
Classifier: Intended Audience :: Developers
Classifier: Intended Audience :: System Administrators
Classifier: Topic :: Software Development :: Build Tools
Classifier: Framework :: Django
Classifier: License :: OSI Approved :: MIT License
Classifier: Programming Language :: Python :: 3
Classifier: Programming Language :: Python :: 3.3
Classifier: Programming Language :: Python :: 3.4
Classifier: Programming Language :: Python :: 3.5
Requires-Dist: django
Provides-Extra: dev
Provides-Extra: test
